digitalearth/__init__.py
digitalearth/map.py
digitalearth/static.py
digitalearth-0.1.11.dist-info/AUTHORS.rst
digitalearth-0.1.11.dist-info/LICENSE.md
digitalearth-0.1.11.dist-info/METADATA
digitalearth-0.1.11.dist-info/WHEEL
digitalearth-0.1.11.dist-info/top_level.txt
digitalearth-0.1.11.dist-info/RECORD
