Metadata-Version: 2.1
Name: digitalearth
Version: 0.1.11
Summary: visualization package
Home-page: https://github.com/MAfarrag/digitalearth
Author: Mostafa Farrag
Author-email: moah.farag@gmail.come
License: GNU General Public License v3
Keywords: matplotlib,maps,visualization
Classifier: Development Status :: 5 - Production/Stable
Classifier: Environment :: Console
Classifier: License :: OSI Approved :: GNU General Public License v3 (GPLv3)
Classifier: Natural Language :: English
Classifier: Programming Language :: Python :: 3
Classifier: Programming Language :: Python :: 3.7
Classifier: Programming Language :: Python :: 3.8
Classifier: Programming Language :: Python :: 3.9
Classifier: Topic :: Scientific/Engineering :: Visualization
Classifier: Intended Audience :: Science/Research
Classifier: Intended Audience :: Developers
License-File: LICENSE.md
License-File: AUTHORS.rst
Requires-Dist: cleopatra (>=0.2.7)
Requires-Dist: gdal (>=3.5.3)
Requires-Dist: geopandas (>=0.12.2)
Requires-Dist: geoplot (>=0.5.1)
Requires-Dist: loguru (>=0.6.0)
Requires-Dist: numpy (>=1.24.1)
Requires-Dist: pip (>=22.3.1)
Requires-Dist: pyramids-gis (>=0.3.2)
